Metadata-Version: 2.1
Name: evatr-client
Version: 0.2.0
Summary: A client for: https://evatr.bff-online.de/eVatR/
Home-page: https://github.com/CeeDiii/evatr-client
Download-URL: https://github.com/CeeDiii/evatr-client/archive/refs/tags/0.2.0.tar.gz
Author: CeeDiii
License: MIT
Keywords: python,uid,vat,uid prüfung,vat validation,evatr,evatr client,evatr python client
Classifier: Development Status :: 4 - Beta
Classifier: Intended Audience :: Developers
Classifier: Programming Language :: Python :: 3
Classifier: Operating System :: Unix
Classifier: Operating System :: MacOS :: MacOS X
Classifier: Operating System :: Microsoft :: Windows
Requires-Python: >=3.9
License-File: LICENSE.txt
